jira_cli/__init__.py
jira_cli/cli.py
jira_cli/commands/__init__.py
jira_cli/commands/base.py
jira_cli/commands/create.py
jira_simple_cli-1.0.1.dist-info/METADATA
jira_simple_cli-1.0.1.dist-info/WHEEL
jira_simple_cli-1.0.1.dist-info/entry_points.txt
jira_simple_cli-1.0.1.dist-info/top_level.txt
jira_simple_cli-1.0.1.dist-info/RECORD
