Metadata-Version: 2.1
Name: jira-simple-cli
Version: 1.0.1
Summary: A Command Line Interface for Jira
Home-page: https://gitlab.com/mundo03/jira-cli
Author: Edmundo Sanchez
Author-email: zomundo@gmail.com
License: GNU v3.0
Keywords: cli
Platform: UNKNOWN
Classifier: Intended Audience :: Developers
Classifier: Topic :: Utilities
Classifier: License :: Public Domain
Classifier: Natural Language :: English
Classifier: Operating System :: OS Independent
Classifier: Programming Language :: Python :: 3.8
Requires-Dist: jira
Provides-Extra: test
Requires-Dist: pytest ; extra == 'test'
